kazane/__init__.py
kazane/decimate.py
kazane/fftconv.py
kazane/resample.py
kazane/sinc.py
kazane/upsample.py
kazane-1.0.4.dist-info/LICENSE
kazane-1.0.4.dist-info/METADATA
kazane-1.0.4.dist-info/WHEEL
kazane-1.0.4.dist-info/top_level.txt
kazane-1.0.4.dist-info/RECORD
