Metadata-Version: 2.1
Name: kazane
Version: 1.0.4
Home-page: https://github.com/yoyololicon/kazane
Author: Chin-Yun Yu
Author-email: lolimaster.cs03@nctu.edu.tw
Classifier: Programming Language :: Python :: 3
Classifier: License :: OSI Approved :: MIT License
Classifier: Operating System :: OS Independent
License-File: LICENSE
Requires-Dist: torch
